setup.py
distributions/Binomialdistribution.py
distributions/Gaussiandistribution.py
distributions/Generaldistribution.py
distributions/__init__.py
stats4ds_distributions.egg-info/PKG-INFO
stats4ds_distributions.egg-info/SOURCES.txt
stats4ds_distributions.egg-info/dependency_links.txt
stats4ds_distributions.egg-info/not-zip-safe
stats4ds_distributions.egg-info/top_level.txt